gnetclisdk/auth.py
gnetclisdk/client.py
gnetclisdk/config.py
gnetclisdk/exceptions.py
gnetclisdk/interceptors.py
gnetclisdk/starter.py
gnetclisdk/proto/server_pb2.py
gnetclisdk/proto/server_pb2.pyi
gnetclisdk/proto/server_pb2_grpc.py
gnetclisdk-1.2.5.dist-info/METADATA
gnetclisdk-1.2.5.dist-info/WHEEL
gnetclisdk-1.2.5.dist-info/top_level.txt
gnetclisdk-1.2.5.dist-info/RECORD
