Metadata-Version: 2.4
Name: gnetclisdk
Version: 1.2.5
Summary: Client for Gnetcli GRPC-server
Home-page: https://github.com/annetutil/gnetcli
Author: Alexander Balezin
Author-email: gescheit12@gmail.com
License: MIT
Classifier: Development Status :: 3 - Alpha
Classifier: Intended Audience :: Developers
Classifier: License :: OSI Approved :: MIT License
Classifier: Programming Language :: Python :: 3.8
Classifier: Programming Language :: Python :: 3.9
Classifier: Programming Language :: Python :: 3.10
Requires-Dist: protobuf>=4.24.4
Requires-Dist: grpcio>=1.59.2
Requires-Dist: googleapis-common-protos>=1.61.0
Requires-Dist: pyyaml
Dynamic: author
Dynamic: author-email
Dynamic: classifier
Dynamic: description
Dynamic: description-content-type
Dynamic: home-page
Dynamic: license
Dynamic: requires-dist
Dynamic: summary
